pom_parser/__init__.py
pom_parser-0.0.2.dist-info/METADATA
pom_parser-0.0.2.dist-info/WHEEL
pom_parser-0.0.2.dist-info/RECORD
